multiutils/__init__.py
multiutils/all.py
multiutils/animations.py
multiutils/pc_infos.py
multiutils/version.py
multiutils-0.1.3.dist-info/METADATA
multiutils-0.1.3.dist-info/WHEEL
multiutils-0.1.3.dist-info/top_level.txt
multiutils-0.1.3.dist-info/RECORD
