Metadata-Version: 2.4
Name: multiutils
Version: 0.1.3
Summary: A library that have a lot of fonctions
Author-email: FreakyFDP <you@example.com>
Requires-Python: >=3.7
Dynamic: requires-python
